{
    "type": "article",
    "id": 229,
    "tags": [
        {
            "tag-id": 513,
            "tag-name": "刺杀"
        },
        {
            "tag-id": 483,
            "tag-name": "64"
        },
        {
            "tag-id": 510,
            "tag-name": "外国友人"
        },
        {
            "tag-id": 531,
            "tag-name": "乳共"
        }
    ],
    "relatedQuestions": [
        {
            "title": "乳包群体由于维尼的苛政而逐渐壮大，现已成为一个“泼聚力量”的群体。那么什么词适合做乳包者的简称？",
            "id": 1940
        },
        {
            "title": "长者为什么说要学“习”一个？",
            "id": 571
        },
        {
            "title": "如果让你二选一，你愿做一个沉迷二次元的废宅还是一个随时可能被枪毙的反动分子？",
            "id": 984
        },
        {
            "title": "请问一下大家对于赵国的态度：是逃离还是拯救？如何看待图片中的两个针锋相对的观点呢？",
            "id": 3129
        },
        {
            "title": "Bilibili还是不是一个纯粹的娱乐社区",
            "id": 2413
        },
        {
            "title": "膜乎会不会是一个钓鱼执法网站",
            "id": 767
        },
        {
            "title": "如果有一天，中国真的不幸成为了一个事实上的法西斯国家，大家会怎么做？",
            "id": 2590
        },
        {
            "title": "如果长者在某一天正式加入了膜乎，是否应该给牠一个特殊钦定账号？享受钦定特效和特殊权限？",
            "id": 1402
        },
        {
            "title": "如何才能让一个完全没接触过膜蛤文化的女生变成膜法师？",
            "id": 760
        },
        {
            "title": "介于目前小粉红太多，美国大学是不是应该出台一个政策，强制中国留学生参加政治、哲学或者法律史课程",
            "id": 2248
        },
        {
            "title": "这是一个测试问题",
            "id": 1
        }
    ],
    "detail": {
        "title": "小金和小萨勒曼，一个擅长炮决一个擅长肢解，两个最牛八零后。",
        "body": "<p><img src=\"/uploads/ueditor/20181020/1540012243107813.png\" title=\"1540012243107813.png\" alt=\"Screenshot_3.png\"></p>",
        "author": 1393,
        "voters": [],
        "publishTime": "2018-10-20T00:00:00.000Z",
        "modifyTime": "2018-10-20T00:00:00.000Z"
    },
    "comments": [
        {
            "author": {
                "user-id": 1888,
                "user-name": "见得多了"
            },
            "body": "共产主义和穆斯林国家乃当今世界两大毒瘤",
            "publishTime": "2018-10-20T05:29:00.000Z",
            "modifyTime": "2018-10-20T05:29:00.000Z"
        }
    ]
}
