{
    "type": "question",
    "id": 1792,
    "tags": [
        {
            "tag-id": 312,
            "tag-name": "美国"
        },
        {
            "tag-id": 143,
            "tag-name": "中国"
        }
    ],
    "detail": {
        "title": "中美此次贸易战结果会如何？",
        "body": "<p>7月6日关税惩罚将生效，贸易战看来已经无法避免了。那么各位认为结果会如何呢？</p>",
        "author": 1116,
        "link": null,
        "comments": 0,
        "publishTime": "2018-07-01T00:00:00.000Z",
        "modifyTime": "2018-07-01T00:00:00.000Z"
    },
    "answers": [
        {
            "author": 1090,
            "body": "如图<br>\n<div class=\"aw-upload-img-list active\">\n\t<a href=\"/uploads/answer/20180701/faca34b8b28361cfa0370f715608c6b2.jpg\" target=\"_blank\" data-fancybox-group=\"thumb\" rel=\"lightbox\"><img src=\"/uploads/answer/20180701/faca34b8b28361cfa0370f715608c6b2.jpg\" class=\"img-polaroid\" title=\"56796eea758c8e72177b1441f524a127.jpg\" alt=\"56796eea758c8e72177b1441f524a127.jpg\"></a>\n</div>",
            "folded": true,
            "agree-by": [
                {
                    "user-id": 632,
                    "user-name": "Excited_Wallce"
                },
                {
                    "user-id": 567,
                    "user-name": "江泽妮可"
                },
                {
                    "user-id": 54,
                    "user-name": "Rayista"
                },
                {
                    "user-id": 1441,
                    "user-name": "傻个儿王"
                },
                {
                    "user-id": 915,
                    "user-name": "龙蛤前辈"
                },
                {
                    "user-id": 1393,
                    "user-name": "Chinese淫"
                },
                {
                    "user-id": 1052,
                    "user-name": "膜法禁书目录"
                },
                {
                    "user-id": 1447,
                    "user-name": "今日不知我是我"
                },
                {
                    "user-id": 765,
                    "user-name": "习习蛤虫合"
                },
                {
                    "user-id": 1662,
                    "user-name": "dqyht"
                }
            ],
            "using-mobile-phone": true,
            "comments": 3,
            "publishTime": "2018-07-01T00:00:00.000Z",
            "modifyTime": "2018-07-01T00:00:00.000Z"
        },
        {
            "author": 1087,
            "body": "<p>如果川普顶住国内国际压力保持政策不被赶下台的话，我觉得中国首先撑不住。</p><p>中国这几年官方自我膨胀的厉害，宣传得小粉红天天做中国梦脚踢美帝拳打欧盟，实际上还是一个百分之九十以上人口的收入都不够交个税的两极分化极端严重的准专制国家，经济结构脆弱的很，半壁江山是房地产。</p>",
            "folded": false,
            "agree-by": [
                {
                    "user-id": 1393,
                    "user-name": "Chinese淫"
                },
                {
                    "user-id": 602,
                    "user-name": "釭鐸鈱"
                },
                {
                    "user-id": 1052,
                    "user-name": "膜法禁书目录"
                },
                {
                    "user-id": 80,
                    "user-name": "linkhoo"
                }
            ],
            "using-mobile-phone": false,
            "comments": 0,
            "publishTime": "2018-07-01T00:00:00.000Z",
            "modifyTime": "2018-07-01T00:00:00.000Z"
        },
        {
            "author": 1496,
            "body": "<p>是时候收复台湾啦</p>",
            "folded": false,
            "agree-by": [],
            "using-mobile-phone": false,
            "comments": 0,
            "publishTime": "2018-07-02T00:00:00.000Z",
            "modifyTime": "2018-07-02T00:00:00.000Z"
        },
        {
            "author": 1523,
            "body": "<p>中美貿易戰的結果就是趙國物價飛漲，退出WTO，然後閉關鎖國<br></p>",
            "folded": false,
            "agree-by": [],
            "using-mobile-phone": false,
            "comments": 0,
            "publishTime": "2018-07-08T00:00:00.000Z",
            "modifyTime": "2018-07-08T00:00:00.000Z"
        },
        {
            "author": 1178,
            "body": "<p>如果全面开战 就意味着 第三次世界大战</p><p>从目前来看 还是特朗普政府想要达到自己政治目的 的一个发起手段，</p><p>胜负并没有什么实际意义，结果无非都是 伤敌一千自损八百而已</p>",
            "folded": false,
            "agree-by": [],
            "using-mobile-phone": false,
            "comments": 0,
            "publishTime": "2018-07-02T00:00:00.000Z",
            "modifyTime": "2018-07-02T00:00:00.000Z"
        }
    ],
    "relatedQuestions": [
        {
            "title": "如何看待贸易战先苦后甜的说法",
            "id": 2575
        },
        {
            "title": "如何看待美中第二次贸易战？",
            "id": 1612
        },
        {
            "title": "如何看待新签订的中美贸易协定？",
            "id": 911
        },
        {
            "title": "包子和包子的政府和中美贸易战是否脱离不了关系？",
            "id": 3607
        },
        {
            "title": "如何评价这个以贸易战为题材的六格漫画？里面的刁大犬通过噶韭菜加血",
            "id": 3079
        },
        {
            "title": "如何评价中美双方就朝鲜半岛问题交换意见？",
            "id": 671
        },
        {
            "title": "关于中美大战",
            "id": 3165
        },
        {
            "title": "坏球时报说这次贸易战是持久战，各位准备好了吗？",
            "id": 3518
        },
        {
            "title": "蛮族勇士评对美贸易战白皮书，大家分析下靠不靠谱？",
            "id": 2888
        },
        {
            "title": "如何看待杰克马关于贸易战的评论？",
            "id": 3032
        }
    ],
    "questionStatus": {
        "last-active-time": "2018-07-07T16:15:00.000Z",
        "views": 436,
        "concerns": 6
    }
}
