{
    "type": "question",
    "id": 2362,
    "tags": [
        {
            "tag-id": 160,
            "tag-name": "乳包"
        },
        {
            "tag-id": 4,
            "tag-name": "膜蛤"
        }
    ],
    "detail": {
        "title": "膜乎是否应该以更强硬的态度应对混入队伍的五毛精赵粉红？",
        "body": "显然民主自由不能成为藏污纳垢的保护伞，开放宽容也不是没有限度的。<br>\n<br>\n膜乎作为一个Hath的交流平台，即非政党更非国家，而是同类人的聚集地，因此清除与我们的共识有根本冲突的人士是天经地义。<br>\n<br>\n我们Hath的基本共识是文明开放、民主自由。由此衍生出的民主革命和改良主义都是我们的朋友。而公然膜包，或为当前体制涂脂抹粉，都是我们无法容忍的敌对行为。<br>\n<br>\n因此我个人希望膜乎对有强烈粉红倾向的用户采取封禁措施，对膜包行为严惩不贷！",
        "author": 1441,
        "link": null,
        "comments": 0,
        "publishTime": "2018-08-25T00:00:00.000Z",
        "modifyTime": "2018-08-25T00:00:00.000Z"
    },
    "answers": [
        {
            "author": 1570,
            "body": "<p>不好意思，今天我就要得罪一下膜乎的Hath。</p><p><br></p><p>从我上个的问题<a title=\"/question/2287\" href=\"/question/2287\" target=\"_blank\">/question/2287</a>和之前的观察来看，多数膜乎用户都还倾向于开明专制式的政治体制，甚至不少人还都认为只是刁一人的问题，对长者时期的怀念其实就和一些人觉得德三军服好帅/苏联军乐好雄壮而开始崇拜纳粹/苏联一样。</p><p><br></p><p>养猪场不管换什么饲养员给什么样的饲料，猪的命运都是一样的。既然是猪就不存在所谓文明开放、民主自由的前提。现在抓飞碟不如自己销号。</p>",
            "agree-by": [
                {
                    "user-id": 1561,
                    "user-name": "ま蛤ろす"
                },
                {
                    "user-id": 1498,
                    "user-name": "冴月麟"
                },
                {
                    "user-id": 881,
                    "user-name": "江蛤蟆是坠吼的"
                },
                {
                    "user-id": 1701,
                    "user-name": "潘静雯"
                },
                {
                    "user-id": 1426,
                    "user-name": "hei544n"
                }
            ],
            "using-mobile-phone": false,
            "comments": 4,
            "publishTime": "2018-08-25T00:00:00.000Z",
            "modifyTime": "2018-08-25T00:00:00.000Z"
        },
        {
            "author": 1572,
            "body": "<p>是。<br></p>",
            "agree-by": [
                {
                    "user-id": 881,
                    "user-name": "江蛤蟆是坠吼的"
                },
                {
                    "user-id": 902,
                    "user-name": "小熊维尼"
                }
            ],
            "using-mobile-phone": false,
            "comments": 2,
            "publishTime": "2018-08-25T00:00:00.000Z",
            "modifyTime": "2018-08-25T00:00:00.000Z"
        },
        {
            "author": 1467,
            "body": "支持一个",
            "agree-by": [
                {
                    "user-id": 1426,
                    "user-name": "hei544n"
                }
            ],
            "using-mobile-phone": true,
            "comments": 0,
            "publishTime": "2018-08-25T00:00:00.000Z",
            "modifyTime": "2018-08-25T00:00:00.000Z"
        },
        {
            "author": 1944,
            "body": "<p>支持支持</p><p>麻利的</p><p>别光说不做啊</p>",
            "agree-by": [],
            "using-mobile-phone": false,
            "comments": 6,
            "publishTime": "2018-08-25T00:00:00.000Z",
            "modifyTime": "2018-08-25T00:00:00.000Z"
        }
    ],
    "relatedQuestions": [
        {
            "title": "如何看待部分膜乎用户盲目反共？",
            "id": 1250
        },
        {
            "title": "江主席是否知道有蛤丝这一群体？",
            "id": 420
        },
        {
            "title": "小粉红群体有哪些代表性观点？",
            "id": 684
        },
        {
            "title": "我不希望膜乎变成第二个品葱！",
            "id": 2990
        },
        {
            "title": "假如张宝华现在还是香港记者，采访包子问他是否打算无限连任，会发生什么？",
            "id": 1252
        },
        {
            "title": "膜乎会不会被续？",
            "id": 120
        },
        {
            "title": "应该活摘恶习身体的哪个部位，莱献给长者？",
            "id": 1418
        },
        {
            "title": "感觉最近膜乎里混入一些粉红蛆，管理员是不是该给予封号并告示天下的奖励了？",
            "id": 1239
        },
        {
            "title": "膜乎似乎很没深度，老是膜来膜去的，有意思么？",
            "id": 2600
        },
        {
            "title": "政府能强行关闭膜乎吗？",
            "id": 542
        },
        {
            "title": "吃包子应该怎么吃？搭配什么更好吃？",
            "id": 421
        }
    ],
    "questionStatus": {
        "last-active-time": "2018-08-25T12:39:00.000Z",
        "views": 407,
        "concerns": 7
    }
}
