{
    "type": "question",
    "id": 2721,
    "tags": [
        {
            "tag-id": 143,
            "tag-name": "中国"
        },
        {
            "tag-id": 502,
            "tag-name": "中国梦"
        }
    ],
    "detail": {
        "title": "如何看待“哮天犬對黨忠誠”事件？",
        "body": "<p>以後要不就把愛國批小將稱為“哮天犬”好了？<img src=\"/uploads/ueditor/20180919/1537318967105913.jpg\" title=\"1537318967105913.jpg\" alt=\"M20180919_085857_275.jpg\"></p>",
        "author": 1393,
        "link": null,
        "comments": 0,
        "publishTime": "2018-09-19T00:00:00.000Z",
        "modifyTime": "2018-09-19T00:00:00.000Z"
    },
    "answers": [
        {
            "author": 1385,
            "body": "<p>我是党的一条狗，守在党的大门口，叫我咬谁就咬谁，叫咬几口咬几口</p>",
            "folded": false,
            "agree-by": [
                {
                    "user-id": 1393,
                    "user-name": "Chinese淫"
                },
                {
                    "user-id": 2140,
                    "user-name": "Renaissance"
                },
                {
                    "user-id": 1674,
                    "user-name": "二百斤"
                },
                {
                    "user-id": 2174,
                    "user-name": "Naiiiiiive"
                },
                {
                    "user-id": 2217,
                    "user-name": "境内反华势力"
                },
                {
                    "user-id": 40,
                    "user-name": "江边沼泽的村民"
                },
                {
                    "user-id": 1888,
                    "user-name": "见得多了"
                }
            ],
            "using-mobile-phone": false,
            "comments": 0,
            "publishTime": "2018-09-19T00:00:00.000Z",
            "modifyTime": "2018-09-19T00:00:00.000Z"
        },
        {
            "author": 430,
            "body": "<div class=\"aw-upload-img-list active\">\n\t<a href=\"/uploads/answer/20180919/5417d360358be4cb301528db35f00a71.jpg\" target=\"_blank\" data-fancybox-group=\"thumb\" rel=\"lightbox\"><img src=\"/uploads/answer/20180919/5417d360358be4cb301528db35f00a71.jpg\" class=\"img-polaroid\" title=\"IMG_-h9c9bd.jpg\" alt=\"IMG_-h9c9bd.jpg\"></a>\n</div>",
            "folded": false,
            "agree-by": [
                {
                    "user-id": 1674,
                    "user-name": "二百斤"
                },
                {
                    "user-id": 881,
                    "user-name": "江蛤蟆是坠吼的"
                },
                {
                    "user-id": 2217,
                    "user-name": "境内反华势力"
                },
                {
                    "user-id": 40,
                    "user-name": "江边沼泽的村民"
                },
                {
                    "user-id": 1888,
                    "user-name": "见得多了"
                }
            ],
            "using-mobile-phone": true,
            "comments": 0,
            "publishTime": "2018-09-19T00:00:00.000Z",
            "modifyTime": "2018-09-19T00:00:00.000Z"
        },
        {
            "author": 2164,
            "body": "我们清国人最迫切需要的可贵的品质就是说真话、说实话。——鲁迅",
            "folded": false,
            "agree-by": [
                {
                    "user-id": 1393,
                    "user-name": "Chinese淫"
                },
                {
                    "user-id": 1674,
                    "user-name": "二百斤"
                },
                {
                    "user-id": 1888,
                    "user-name": "见得多了"
                }
            ],
            "using-mobile-phone": true,
            "comments": 0,
            "publishTime": "2018-09-19T00:00:00.000Z",
            "modifyTime": "2018-09-19T00:00:00.000Z"
        },
        {
            "author": 881,
            "body": "<p>习大犬，对党忠诚</p>",
            "folded": false,
            "agree-by": [
                {
                    "user-id": 673,
                    "user-name": "藻葉"
                },
                {
                    "user-id": 40,
                    "user-name": "江边沼泽的村民"
                }
            ],
            "using-mobile-phone": false,
            "comments": 0,
            "publishTime": "2018-09-19T00:00:00.000Z",
            "modifyTime": "2018-09-19T00:00:00.000Z"
        },
        {
            "author": 673,
            "body": "<p>这是侮辱中国神话形象哮天犬。。</p>",
            "folded": false,
            "agree-by": [
                {
                    "user-id": 881,
                    "user-name": "江蛤蟆是坠吼的"
                }
            ],
            "using-mobile-phone": false,
            "comments": 0,
            "publishTime": "2018-09-19T00:00:00.000Z",
            "modifyTime": "2018-09-19T00:00:00.000Z"
        }
    ],
    "relatedQuestions": [
        {
            "title": "如何看待部分膜乎用户盲目反共？",
            "id": 1250
        },
        {
            "title": "如何看待网络上“你支”“支国””支豚“此类称呼方式？",
            "id": 1690
        },
        {
            "title": "怎样看待膜包的人?",
            "id": 478
        },
        {
            "title": "如何看待习近平的三个志愿都填清华？",
            "id": 1731
        },
        {
            "title": "如何看待包子最近提倡崇尚英雄，中华民族需要英雄",
            "id": 1000
        },
        {
            "title": "如何看待微博禁止同性恋？",
            "id": 376
        },
        {
            "title": "如何看待“小粉红”群体？",
            "id": 230
        },
        {
            "title": "如何看待沪独行为？",
            "id": 2253
        },
        {
            "title": "如何看待普京送习近平红色球衣又邀请其尝蜂蜜？",
            "id": 2605
        },
        {
            "title": "如何看待hath低龄化以及无脑跟风膜？",
            "id": 130
        },
        {
            "title": "如何看待五四北大贴出批评习近平的实名大字报？",
            "id": 916
        }
    ],
    "questionStatus": {
        "last-active-time": "2018-09-19T08:28:00.000Z",
        "views": 520,
        "concerns": 6
    }
}
