{
    "type": "question",
    "id": 306,
    "tags": [
        {
            "tag-id": 26,
            "tag-name": "如何评价 X"
        }
    ],
    "detail": {
        "title": "如何看待2017年底北京排华（驱逐低端人口）事件",
        "body": "",
        "author": 642,
        "link": null,
        "comments": 0,
        "publishTime": "2018-04-06T00:00:00.000Z",
        "modifyTime": "2018-04-06T00:00:00.000Z"
    },
    "answers": [
        {
            "author": 63,
            "body": "亲不亲，阶级分。",
            "agree-by": [
                {
                    "user-id": 56,
                    "user-name": "globalHe"
                },
                {
                    "user-id": 504,
                    "user-name": "在你后面的点点"
                },
                {
                    "user-id": 567,
                    "user-name": "江泽妮可"
                },
                {
                    "user-id": 327,
                    "user-name": "petersuen"
                },
                {
                    "user-id": 3,
                    "user-name": "多实子酱"
                },
                {
                    "user-id": 642,
                    "user-name": "黑泽露比"
                }
            ],
            "using-mobile-phone": false,
            "comments": 0,
            "publishTime": "2018-04-09T00:00:00.000Z",
            "modifyTime": "2018-04-09T00:00:00.000Z"
        },
        {
            "author": 56,
            "body": "没听说过<br>\n<br>\n更新<br>\n看到标题里面还有个驱逐低端人口就知道了2333<br>\n实名赞同新ha社的答案",
            "agree-by": [
                {
                    "user-id": 642,
                    "user-name": "黑泽露比"
                },
                {
                    "user-id": 327,
                    "user-name": "petersuen"
                }
            ],
            "using-mobile-phone": false,
            "comments": 0,
            "publishTime": "2018-04-06T00:00:00.000Z",
            "modifyTime": "2018-04-06T00:00:00.000Z"
        },
        {
            "author": -1,
            "body": "香港公房.jpg",
            "agree-by": [],
            "using-mobile-phone": true,
            "comments": 0,
            "publishTime": "2018-04-06T00:00:00.000Z",
            "modifyTime": "2018-04-06T00:00:00.000Z"
        },
        {
            "author": 353,
            "body": "盛京的大善人呐",
            "agree-by": [],
            "using-mobile-phone": true,
            "comments": 0,
            "publishTime": "2018-04-09T00:00:00.000Z",
            "modifyTime": "2018-04-09T00:00:00.000Z"
        }
    ],
    "relatedQuestions": [
        {
            "title": "如何看待部分膜乎用户盲目反共？",
            "id": 1250
        },
        {
            "title": "如何看待网络上“你支”“支国””支豚“此类称呼方式？",
            "id": 1690
        },
        {
            "title": "怎样看待膜包的人?",
            "id": 478
        },
        {
            "title": "如何看待习近平的三个志愿都填清华？",
            "id": 1731
        },
        {
            "title": "如何看待包子最近提倡崇尚英雄，中华民族需要英雄",
            "id": 1000
        },
        {
            "title": "如何看待微博禁止同性恋？",
            "id": 376
        },
        {
            "title": "如何看待沪独行为？",
            "id": 2253
        },
        {
            "title": "如何看待“小粉红”群体？",
            "id": 230
        },
        {
            "title": "如何看待hath低龄化以及无脑跟风膜？",
            "id": 130
        },
        {
            "title": "如何看待普京送习近平红色球衣又邀请其尝蜂蜜？",
            "id": 2605
        },
        {
            "title": "如何评价北京大学林校长读错别字，然后道歉？",
            "id": 663
        }
    ],
    "questionStatus": {
        "last-active-time": "2018-04-09T04:01:00.000Z",
        "views": 388,
        "concerns": 5
    }
}
