{
    "type": "question",
    "id": 3202,
    "tags": [
        {
            "tag-id": 596,
            "tag-name": "艺术"
        }
    ],
    "detail": {
        "title": "有没有墙外豆瓣？",
        "body": "<p>豆瓣上没有情色小说和av以及禁书和h漫h动画的打分，</p><p>这些缺失的名单数量可不少，</p><p>虽说大多数都是不及格连5分都没有的作品，</p><p>但还是有不少可以高达9分以上吧。<br></p>",
        "author": null,
        "link": null,
        "comments": 0,
        "publishTime": "2018-10-06T00:00:00.000Z",
        "modifyTime": "2018-10-06T00:00:00.000Z"
    },
    "answers": [
        {
            "author": 1441,
            "body": "我也想知道",
            "agree-by": [],
            "using-mobile-phone": true,
            "comments": 0,
            "publishTime": "2018-10-06T00:00:00.000Z",
            "modifyTime": "2018-10-06T00:00:00.000Z"
        },
        {
            "author": null,
            "body": "豆瓣排除水军算是公平的了。西方那些评分网站都快被圣母婊们玩臭了。烂番茄还不如豆瓣",
            "agree-by": [],
            "using-mobile-phone": true,
            "comments": 0,
            "publishTime": "2018-10-07T00:00:00.000Z",
            "modifyTime": "2018-10-07T00:00:00.000Z"
        }
    ],
    "relatedQuestions": [
        {
            "title": "在墙外膜蛤乳包真的永远安全吗？",
            "id": 3628
        },
        {
            "title": "在墙外乳包会被迫失踪吗？",
            "id": 2364
        },
        {
            "title": "如何看待当今墙外中文圈的风气？",
            "id": 1450
        },
        {
            "title": "如何评价墙外“民主人士”？",
            "id": 1788
        },
        {
            "title": "有哪些靠谱的墙外中文媒体？",
            "id": 1808
        },
        {
            "title": "墙外有哪些很好用的社交软件？",
            "id": 1507
        },
        {
            "title": "你在墙内墙外见过哪些和长者有关的段子？",
            "id": 382
        },
        {
            "title": "在墙外问墙内可以提问的问题有意义吗？",
            "id": 1681
        }
    ],
    "questionStatus": {
        "last-active-time": "2018-10-06T16:21:00.000Z",
        "views": 205,
        "concerns": 3
    }
}
