{
    "type": "question",
    "id": 3266,
    "tags": [
        {
            "tag-id": 620,
            "tag-name": "彭定康"
        },
        {
            "tag-id": 4,
            "tag-name": "膜蛤"
        }
    ],
    "detail": {
        "title": "为什么姓彭的人都喜欢无中生有？",
        "body": "十年前是彭定康，如今是彭斯，都是彭家人！\n\t\t\t\t\t\t\t\t\t\t\t\t\t\t\t\t<div class=\"aw-upload-img-list\">\n\t\t\t\t\t\t\t\t\t\t\t\t\t\t\t\t\t\t\t\t\t\t\t\t\t<a href=\"/uploads/questions/20181008/3c746a9b974c2864411e6abd3af8bc3a.jpg\" target=\"_blank\" data-fancybox-group=\"thumb\" rel=\"lightbox\"><img src=\"/uploads/questions/20181008/3c746a9b974c2864411e6abd3af8bc3a.jpg\" class=\"img-thumbnail\" alt=\"DCB6AB23CE8B82CB07074CEC098DE686.jpg\"></a>\n\t\t\t\t\t\t\t\t\t\t\t\t\t\t\t\t\t\t\t\t\t\t\t\t</div>",
        "author": 1441,
        "link": null,
        "comments": 0,
        "publishTime": "2018-10-09T00:00:00.000Z",
        "modifyTime": "2018-10-09T00:00:00.000Z"
    },
    "answers": [
        {
            "author": 2558,
            "body": "<p>还有个姓彭的喜欢唱歌</p>",
            "folded": false,
            "agree-by": [
                {
                    "user-id": 1888,
                    "user-name": "见得多了"
                },
                {
                    "user-id": 1561,
                    "user-name": "ま蛤ろす"
                },
                {
                    "user-id": 295,
                    "user-name": "邓小平"
                }
            ],
            "using-mobile-phone": false,
            "comments": 0,
            "publishTime": "2018-10-09T00:00:00.000Z",
            "modifyTime": "2018-10-09T00:00:00.000Z"
        },
        {
            "author": 2560,
            "body": "<p>因为最近美国只要发声，外交部基本都说他无中生有造谣诽谤</p>",
            "folded": false,
            "agree-by": [],
            "using-mobile-phone": false,
            "comments": 0,
            "publishTime": "2018-10-09T00:00:00.000Z",
            "modifyTime": "2018-10-09T00:00:00.000Z"
        },
        {
            "author": 2304,
            "body": "<p>当然是无中生有啦，不无中生有哪里会多出那么多种声乐唱法。</p>",
            "folded": false,
            "agree-by": [],
            "using-mobile-phone": false,
            "comments": 0,
            "publishTime": "2018-10-09T00:00:00.000Z",
            "modifyTime": "2018-10-09T00:00:00.000Z"
        }
    ],
    "relatedQuestions": [
        {
            "title": "很喜欢长者但是讨厌共产党怎么办",
            "id": 806
        },
        {
            "title": "如何看待某国家政府网站说“从下个月起工资少了但钱还是你的”这句话？难道包包大人喜欢吃嫩韭菜？",
            "id": 2418
        },
        {
            "title": "小学文化大字不识、喜欢在公共场合宽衣的人算不算低端人口？",
            "id": 2531
        },
        {
            "title": "65岁是学生，最近有在读书，喜欢萨格尔王乱宽衣，这样的我能交到女朋友吗？",
            "id": 410
        },
        {
            "title": "各位喜欢管家吗？",
            "id": 2712
        },
        {
            "title": "喜欢日本是精日，本人喜欢英国，是精英？",
            "id": 3055
        },
        {
            "title": "为什么萨格尔王喜欢宽衣？",
            "id": 572
        },
        {
            "title": "大家喜欢什么样的娱乐性话题啊?",
            "id": 1403
        },
        {
            "title": "长者最喜欢读哪些书？",
            "id": 1128
        },
        {
            "title": "当朝皇上喜欢土味政治口号，大家都来编点为中国梦做贡献？",
            "id": 2707
        },
        {
            "title": "hath们有没有特别喜欢的电子游戏和游戏公司",
            "id": 3978
        }
    ],
    "questionStatus": {
        "last-active-time": "2018-10-08T22:10:00.000Z",
        "views": 326,
        "concerns": 4
    }
}
