{
    "type": "question",
    "id": 3680,
    "tags": [
        {
            "tag-id": 729,
            "tag-name": "日常"
        },
        {
            "tag-id": 215,
            "tag-name": "膜包"
        },
        {
            "tag-id": 794,
            "tag-name": "膜包小鬼"
        }
    ],
    "detail": {
        "title": "为什么膜包小鬼学会了复读？",
        "body": "<p><img src=\"/uploads/ueditor/20181019/1539955146579480.png\" title=\"1539955146579480.png\" alt=\"Screenshot_2018-10-19-21-01-49-1468698035.png\"><img src=\"/uploads/ueditor/20181019/1539955160435198.png\" title=\"1539955160435198.png\" alt=\"Screenshot_2018-10-19-21-06-44-0535994534.png\"></p>",
        "author": 1385,
        "link": null,
        "comments": 0,
        "publishTime": "2018-10-19T00:00:00.000Z",
        "modifyTime": "2018-10-19T00:00:00.000Z"
    },
    "answers": [
        {
            "author": 2304,
            "body": "<p>包轮大法要求弟子超时空循环，于是便有了背书单和拉清单的无限重复。在语气上岿然不动，这样才能在 89.64% 的螳臂当车的歹徒的面前保持最大限度的克制！</p>",
            "agree-by": [
                {
                    "user-id": 1393,
                    "user-name": "Chinese淫"
                },
                {
                    "user-id": 2456,
                    "user-name": "bisհi"
                },
                {
                    "user-id": 2739,
                    "user-name": "Nest"
                },
                {
                    "user-id": 1674,
                    "user-name": "二百斤"
                },
                {
                    "user-id": 1052,
                    "user-name": "膜法禁书目录"
                }
            ],
            "using-mobile-phone": false,
            "comments": 0,
            "publishTime": "2018-10-19T00:00:00.000Z",
            "modifyTime": "2018-10-19T00:00:00.000Z"
        },
        {
            "author": 2226,
            "body": "因为，人类的本质是，复读机！",
            "agree-by": [
                {
                    "user-id": 881,
                    "user-name": "江蛤蟆是坠吼的"
                },
                {
                    "user-id": 1674,
                    "user-name": "二百斤"
                },
                {
                    "user-id": 1052,
                    "user-name": "膜法禁书目录"
                }
            ],
            "using-mobile-phone": true,
            "comments": 0,
            "publishTime": "2018-10-19T00:00:00.000Z",
            "modifyTime": "2018-10-19T00:00:00.000Z"
        },
        {
            "author": 2143,
            "body": "<p>2017年11月加入，搞了一年怎么才11个关注呢？</p>",
            "agree-by": [
                {
                    "user-id": 1674,
                    "user-name": "二百斤"
                }
            ],
            "using-mobile-phone": false,
            "comments": 0,
            "publishTime": "2018-10-19T00:00:00.000Z",
            "modifyTime": "2018-10-19T00:00:00.000Z"
        },
        {
            "author": 673,
            "body": "<p>いだいいえんじんしせんいえん</p><p><br></p><p>那个，其实牠是不是VPN坏了。。</p>",
            "agree-by": [
                {
                    "user-id": 9,
                    "user-name": "Wallais_"
                }
            ],
            "using-mobile-phone": false,
            "comments": 0,
            "publishTime": "2018-10-20T00:00:00.000Z",
            "modifyTime": "2018-10-20T00:00:00.000Z"
        },
        {
            "author": null,
            "body": "看他的账号名，正常人类会用这玩意当注册名么？",
            "agree-by": [],
            "using-mobile-phone": true,
            "comments": 0,
            "publishTime": "2018-10-20T00:00:00.000Z",
            "modifyTime": "2018-10-20T00:00:00.000Z"
        },
        {
            "author": 881,
            "body": "<p>一代仁君习圣人</p>",
            "agree-by": [],
            "using-mobile-phone": false,
            "comments": 0,
            "publishTime": "2018-10-20T00:00:00.000Z",
            "modifyTime": "2018-10-20T00:00:00.000Z"
        },
        {
            "author": null,
            "body": "<p>一代仁君习圣人</p>",
            "agree-by": [],
            "using-mobile-phone": false,
            "comments": 0,
            "publishTime": "2018-10-20T00:00:00.000Z",
            "modifyTime": "2018-10-20T00:00:00.000Z"
        },
        {
            "author": null,
            "body": "<p>一代仁君习圣人</p>",
            "agree-by": [],
            "using-mobile-phone": false,
            "comments": 0,
            "publishTime": "2018-10-20T00:00:00.000Z",
            "modifyTime": "2018-10-20T00:00:00.000Z"
        }
    ],
    "relatedQuestions": [
        {
            "title": "怎样看待膜包的人?",
            "id": 478
        },
        {
            "title": "【公平持正，理智膜包】在抑制高房价这个民生议题上，我包的功劳不容抹杀吧？",
            "id": 3386
        },
        {
            "title": "辱包会不会随着时间推移逐渐变成膜包？",
            "id": 3216
        },
        {
            "title": "如何让膜包小鬼放弃膜包转入膜蛤？",
            "id": 864
        },
        {
            "title": "如何評価這個尬膜小鬼的事迹",
            "id": 783
        },
        {
            "title": "怎么看待乳蛤膜包",
            "id": 1405
        },
        {
            "title": "怎样才能膜包？",
            "id": 3294
        },
        {
            "title": "如何看待部分膜包粉红对刁大犬和三胖存在性幻想？",
            "id": 2604
        },
        {
            "title": "如何看待身边的尬膜小鬼？",
            "id": 154
        },
        {
            "title": "膜包能否成Hath的否定性准入条件？",
            "id": 2356
        },
        {
            "title": "请问一下，谁能把包子的经历给补上？重点还要是有一点点膜包（要有反语，明奉实讽）色彩",
            "id": 2165
        }
    ],
    "questionStatus": {
        "last-active-time": "2018-10-20T05:09:00.000Z",
        "views": 426,
        "concerns": 6
    }
}
