{
    "type": "question",
    "id": 3764,
    "tags": [
        {
            "tag-id": 8,
            "tag-name": "政治"
        },
        {
            "tag-id": 831,
            "tag-name": "大清国"
        },
        {
            "tag-id": 832,
            "tag-name": "风评被害"
        }
    ],
    "detail": {
        "title": "大清国到底是从什么时候开始风评被害的？",
        "body": "",
        "author": 1385,
        "link": null,
        "comments": 0,
        "publishTime": "2018-10-22T00:00:00.000Z",
        "modifyTime": "2018-10-22T00:00:00.000Z"
    },
    "answers": [
        {
            "author": null,
            "body": "<p>大清国以屠杀起家，以八旗特权和文字狱贯穿始终，以花式出卖国家利益结束，这朝代的风评不存在被害。</p>",
            "agree-by": [
                {
                    "user-id": 1052,
                    "user-name": "膜法禁书目录"
                },
                {
                    "user-id": 1816,
                    "user-name": "阿虚"
                },
                {
                    "user-id": 1393,
                    "user-name": "Chinese淫"
                },
                {
                    "user-id": 1643,
                    "user-name": "人克坦"
                },
                {
                    "user-id": 2777,
                    "user-name": "维尼无限连任"
                }
            ],
            "using-mobile-phone": false,
            "comments": 0,
            "publishTime": "2018-10-22T00:00:00.000Z",
            "modifyTime": "2018-10-22T00:00:00.000Z"
        },
        {
            "author": 2517,
            "body": "<p>大清从入关就浑身是黑点，这点就无需再度解释了。</p><p>如果题主想问的是近几年的风评被害，这要说起前一阵子被玩坏了的03年电视剧《走向共和》</p><p>剧中充斥着与当代时势惊人相似的人物与台词，例如说最常被引申的“我大清自有国情在此”，</p><p>大概指的就是“特色社会主义核心思想”。</p><p>后因走向共和被玩坏，B站全面禁止了走向共和的搜索，以及相关影片的评论与弹幕。</p><p>如果按照清朝灭亡距今的岁月，已经有106年，这可能意味着我们倒了110年</p>",
            "agree-by": [
                {
                    "user-id": 1020,
                    "user-name": "江军"
                },
                {
                    "user-id": 1393,
                    "user-name": "Chinese淫"
                },
                {
                    "user-id": 1643,
                    "user-name": "人克坦"
                }
            ],
            "using-mobile-phone": false,
            "comments": 0,
            "publishTime": "2018-10-23T00:00:00.000Z",
            "modifyTime": "2018-10-23T00:00:00.000Z"
        },
        {
            "author": 2143,
            "body": "<p>泻药！<br></p><p>从大清建国的时候罢</p>",
            "agree-by": [
                {
                    "user-id": 881,
                    "user-name": "江蛤蟆是坠吼的"
                }
            ],
            "using-mobile-phone": false,
            "comments": 0,
            "publishTime": "2018-10-22T00:00:00.000Z",
            "modifyTime": "2018-10-22T00:00:00.000Z"
        },
        {
            "author": null,
            "body": "风评被害的前提是被害对象和加害者无冤无仇<br>\n<br>\n看来我大清并不满足此条件。所以，只能说我大清活几把该了",
            "agree-by": [
                {
                    "user-id": 1393,
                    "user-name": "Chinese淫"
                }
            ],
            "using-mobile-phone": true,
            "comments": 0,
            "publishTime": "2018-10-23T00:00:00.000Z",
            "modifyTime": "2018-10-23T00:00:00.000Z"
        },
        {
            "author": null,
            "body": "事马来獠口泼的脏水（鸥持），，，",
            "agree-by": [],
            "using-mobile-phone": false,
            "comments": 0,
            "publishTime": "2018-10-22T00:00:00.000Z",
            "modifyTime": "2018-10-22T00:00:00.000Z"
        }
    ],
    "relatedQuestions": [
        {
            "title": "什么时候你对中国的未来最没有信心？",
            "id": 1126
        },
        {
            "title": "港真，面对包子开倒车，我们这个网站到底能做点什么？中国的政治改革有可能到来吗？",
            "id": 1053
        },
        {
            "title": "你是什么时候发现刁大犬是个危险的倒车歹徒的？",
            "id": 2449
        },
        {
            "title": "什么时候才天亮？",
            "id": 930
        },
        {
            "title": "天安门事件到底是谁的错？",
            "id": 1095
        },
        {
            "title": "说到底，习到底想要怎样？",
            "id": 3262
        },
        {
            "title": "3000游客被困日本机场...到底是真新闻还是假新闻？",
            "id": 2539
        },
        {
            "title": "光明的那一天什么时候才倒来呢？",
            "id": 3149
        },
        {
            "title": "社会主义到底有没有可能成功？",
            "id": 1021
        },
        {
            "title": "如何看待人民日报发文《明星什么时候起“不能批评”了？》",
            "id": 2229
        },
        {
            "title": "包子的“人类命运共同体”到底是什么想法？",
            "id": 2608
        }
    ],
    "questionStatus": {
        "last-active-time": "2018-10-24T02:54:00.000Z",
        "views": 251,
        "concerns": 4
    }
}
